<?xml version="1.0" encoding="UTF-8"?>
<vmap:VMAP xmlns:vmap="http://www.iab.net/videosuite/vmap" version="1.0">
    <vmap:AdBreak timeOffset="start" breakType="linear" breakId="midroll">
      <vmap:AdSource id="preroll-ad-1" allowMultipleAds="false" followRedirects="true">
          <vmap:AdTagURI templateType="vast3"><![CDATA[https://cdn.theoplayer.com/demos/ads/vast/dfp-preroll-no-skip.xml]]></vmap:AdTagURI>
      </vmap:AdSource>
    </vmap:AdBreak>
    
    <vmap:AdBreak timeOffset="00:00:15" breakType="linear" breakId="midroll">
      <vmap:AdSource id="midroll-ad-1" allowMultipleAds="false" followRedirects="true">
          <vmap:AdTagURI templateType="vast3"><![CDATA[https://cdn.theoplayer.com/demos/ads/vast/dfp-midroll-no-skip.xml]]></vmap:AdTagURI>
      </vmap:AdSource>
    </vmap:AdBreak>
    
    <vmap:AdBreak timeOffset="end" breakType="linear" breakId="midroll">
      <vmap:AdSource id="postroll-ad-1" allowMultipleAds="false" followRedirects="true">
          <vmap:AdTagURI templateType="vast3"><![CDATA[https://cdn.theoplayer.com/demos/ads/vast/dfp-postroll-no-skip.xml]]></vmap:AdTagURI>
      </vmap:AdSource>
    </vmap:AdBreak>
</vmap:VMAP>